model2c/__init__.py
model2c/pykeras/__init__.py
model2c/pykeras/pykeras.py
model2c/pytorch/__init__.py
model2c/pytorch/pytorch.py
model2c-1.1.1.dist-info/LICENSE
model2c-1.1.1.dist-info/METADATA
model2c-1.1.1.dist-info/WHEEL
model2c-1.1.1.dist-info/top_level.txt
model2c-1.1.1.dist-info/RECORD
