Metadata-Version: 2.1
Name: model2c
Version: 1.1.1
Summary: ML model to low-level inference convertor
Home-page: https://github.com/h3x4g0ns/model2c/tree/main
Author: Ekansh Agrawal
Author-email: agrawalekansh@berkely.edu
Keywords: arduino,python,ml,convertory,torch,keras,raspberrypi
Classifier: Programming Language :: Python :: 3
Classifier: License :: OSI Approved :: MIT License
Classifier: Operating System :: OS Independent
Requires-Python: >=3.6
License-File: LICENSE
